buffalonwb/__init__.py
buffalonwb/_version.py
buffalonwb/add_behavior.py
buffalonwb/add_processed_nlx_data.py
buffalonwb/add_raw_nlx_data.py
buffalonwb/add_units.py
buffalonwb/conversion_module.py
buffalonwb/exceptions.py
buffalonwb/nwb_gui.py
buffalonwb/read_processed_nlx_data.py
buffalonwb/extras/__init__.py
buffalonwb/extras/nwb_to_nex5.py
buffalonwb/extras/spatial_spike_distribution.py
nexfile/__init__.py
nexfile/nexfile.py
nexfile/nexwriter2.py
buffalo_lab_data_to_nwb-0.post0.dev137.dist-info/METADATA
buffalo_lab_data_to_nwb-0.post0.dev137.dist-info/WHEEL
buffalo_lab_data_to_nwb-0.post0.dev137.dist-info/top_level.txt
buffalo_lab_data_to_nwb-0.post0.dev137.dist-info/RECORD
