Metadata-Version: 2.1
Name: buffalo-lab-data-to-nwb
Version: 0.post0.dev137
Summary: A package for converting Buffalo Lab data to the NWB standard
Home-page: https://github.com/ben-dichter-consulting/buffalo-lab-data-to-nwb
Author: Luiz Tauffer, Maija Honig, Ryan Ly, Ben Dichter
Author-email: ben.dichter@gmail.com
License: BSD
Keywords: python HDF HDF5 cross-platform open-data data-format open-source open-science reproducible-research neuroscience neurophysiology
Platform: UNKNOWN
Classifier: Programming Language :: Python
Classifier: Programming Language :: Python :: 3.7
Classifier: License :: OSI Approved :: BSD License
Classifier: Development Status :: 2 - Pre-Alpha
Classifier: Intended Audience :: Developers
Classifier: Intended Audience :: Science/Research
Classifier: Operating System :: Microsoft :: Windows
Classifier: Operating System :: MacOS
Classifier: Operating System :: Unix
Classifier: Topic :: Scientific/Engineering :: Medical Science Apps.
Requires-Dist: pynwb
Requires-Dist: scipy
Requires-Dist: tqdm
Requires-Dist: natsort
Requires-Dist: colorama
